{"info": {"filename": "0536_02_F.jpg", "id": "0536", "gender": "F", "age": 64, "date": "2023-09-13", "skin_type": 5, "sensitive": 0}, "images": {"device": 1, "width": 2448, "height": 3264, "angle": 0, "facepart": 6, "bbox": [1519, 1424, 1853, 2002]}, "annotations": {"r_cheek_pore": 2, "r_cheek_pigmentation": 3}, "equipment": {"r_cheek_moisture": 60.667, "r_cheek_elasticity_R0": 0.275, "r_cheek_elasticity_R1": 0.127, "r_cheek_elasticity_R2": 0.538, "r_cheek_elasticity_R3": 0.315, "r_cheek_elasticity_R4": 0.183, "r_cheek_elasticity_R5": 0.425, "r_cheek_elasticity_R6": 0.536, "r_cheek_elasticity_R7": 0.276, "r_cheek_elasticity_R8": 0.148, "r_cheek_elasticity_R9": 0.04, "r_cheek_elasticity_Q0": 55.0, "r_cheek_elasticity_Q1": 0.469, "r_cheek_elasticity_Q2": 0.352, "r_cheek_elasticity_Q3": 0.117, "r_cheek_pore": 1398.0}}